openclip_client_python/__init__.py
openclip_client_python/client-final-20240515_104948_726.csv
openclip_client_python/client-final-20240515_105037_216.csv
openclip_client_python/client-final-20240515_105426_381.csv
openclip_client_python/client-final-20240515_105901_535.csv
openclip_client_python/client-final-20240515_110417_021.csv
openclip_client_python/client-final-20240515_110812_375.csv
openclip_client_python/client-final-20240515_110837_633.csv
openclip_client_python/client-final-20240515_111029_685.csv
openclip_client_python/client-final-20240515_111233_781.csv
openclip_client_python/client-final-20240515_114253_148.csv
openclip_client_python/client-final-20240515_115055_941.csv
openclip_client_python/client-final-20240515_115130_418.csv
openclip_client_python/client-final-20240515_115453_298.csv
openclip_client_python/client_python.py
openclip_client_python/client_python_middleware.py
openclip_client/client_common.py
openclip_client-0.1.1.dist-info/METADATA
openclip_client-0.1.1.dist-info/WHEEL
openclip_client-0.1.1.dist-info/entry_points.txt
openclip_client-0.1.1.dist-info/RECORD
